PyJsEngine/MiniUtils.py
PyJsEngine/PyJsEngine.py
PyJsEngine/PyJsEngineBase.py
PyJsEngine/__init__.py
PyJsEngine/tools/RequestsJsEngine.py
PyJsEngine/tools/__init__.py
PyJsEngine-0.1.191029.4.dist-info/DESCRIPTION.rst
PyJsEngine-0.1.191029.4.dist-info/METADATA
PyJsEngine-0.1.191029.4.dist-info/RECORD
PyJsEngine-0.1.191029.4.dist-info/WHEEL
PyJsEngine-0.1.191029.4.dist-info/metadata.json
PyJsEngine-0.1.191029.4.dist-info/top_level.txt
pyjse/MiniUtils.py
pyjse/PyJsEngine.py
pyjse/PyJsEngineBase.py
pyjse/__init__.py
pyjse/tools/RequestsJsEngine.py
pyjse/tools/__init__.py
tools/RequestsJsEngine.py
tools/__init__.py
